jentic/apitools/openapi/common/path_security.py
jentic/apitools/openapi/common/py.typed
jentic/apitools/openapi/common/subproc.py
jentic/apitools/openapi/common/uri.py
jentic/apitools/openapi/common/version_detection.py
jentic_openapi_common-1.0.0a34.dist-info/licenses/LICENSE
jentic_openapi_common-1.0.0a34.dist-info/licenses/NOTICE
jentic_openapi_common-1.0.0a34.dist-info/WHEEL
jentic_openapi_common-1.0.0a34.dist-info/METADATA
jentic_openapi_common-1.0.0a34.dist-info/RECORD
